Workbook
Name A1462A1: #REF!
Name Slicer_brand_name: #N/A
Name Slicer_brand_name1: #N/A
Name Slicer_product_category: #N/A

Sheet Sheet1
A1: product_name | B1: brand_name | C1: rating | D1: rating_count | E1: marked_price | F1: discounted_price | G1: sizes | H1: product_link
A2: Slim Fit Casual Shirt | B2: Greenfibre | C2: 0 | D2: 0 | E2: 1699 | F2: 1699 | G2: 38,39,40,42,44 | H2: shirts/greenfibre/greenfibre-men-yellow-slim-fit-checked-casual-shirt/18427366/buy
A3: Men Printed T-shirt | B3: FREESOUL | C3: 0 | D3: 0 | E3: 799 | F3: 799 | G3: S,M,L,XL,XXL | H3: tshirts/freesoul/freesoul-men-white-printed-cotton-t-shirt/18069688/buy
A4: Leather Two Fold Wallet | B4: Da Milano | C4: 0 | D4: 0 | E4: 4499 | F4: 4499 | G4: Onesize | H4: wallets/da-milano/da-milano-women-blue-textured-leather-two-fold-wallet/18013592/buy
A5: Pure Georgette Bandhani Saree | B5: Mitera | C5: 3.6 | D5: 5 | E5: 6727 | F5: 1681 | G5: Onesize | H5: sarees/mitera/mitera-women-sea-green--white-embroidered-pure-georgette-bandhani-saree/17141476/buy
A6: Men Geometric Printed Kurta | B6: Indo Era | C6: 0 | D6: 0 | E6: 2599 | F6: 1429 | G6: S,M,L,XL,XXL | H6: kurtas/indo-era/indo-era-men-lavender-geometric-printed-kurta/17502668/buy
A7: Men Accessory Gift Set | B7: WildHorn | C7: 4.5 | D7: 80 | E7: 2999 | F7: 1049 | G7: Onesize | H7: accessory-gift-set/wildhorn/wildhorn-men-accessory-gift-set/1410357/buy
A8: Self-Design Thermal Set | B8: Kanvin | C8: 4.6 | D8: 42 | E8: 1598 | F8: 1278 | G8: S,M,L,XL,XXL | H8: thermal-set/kanvin/kanvin-off-white-self-design-thermal-set-new2150ow2180/2223155/buy
A9: Men Slim Fit T-shirt | B9: Jack & Jones | C9: 3.7 | D9: 7 | E9: 1299 | F9: 649 | G9: S,M,L,XL,XXL | H9: tshirts/jack--jones/jack--jones-men-blue-slim-fit-t-shirt/15430520/buy
A10: Block Print Pure Georgette Saree | B10: MS RETAIL | C10: 0 | D10: 0 | E10: 1015 | F10: 497 | G10: Onesize | H10: sarees/ms-retail/ms-retail-green--white-pure-georgette-block-print-saree/18467984/buy
A11: Outdoor Rapid-Dry Jacket | B11: HRX by Hrithik Roshan | C11: 4.4 | D11: 186 | E11: 2799 | F11: 1679 | G11: XS,S,M,L,XL | H11: jackets/hrx-by-hrithik-roshan/hrx-by-hrithik-roshan-women-navy-colourblocked-rapid-dry-antimicrobial-outdoor-jacket/11953112/buy
A12: Floral Maxi Dress | B12: Nayo | C12: 4 | D12: 7 | E12: 1999 | F12: 799 | G12: S,M,L,XL,XXL | H12: dresses/nayo/nayo-pink--white-floral-ethnic-maxi-dress/17634118/buy
A13: Women Ribbed Fitted Top | B13: DressBerry | C13: 4.2 | D13: 252 | E13: 999 | F13: 399 | G13: XS,S,M,L,XL | H13: tops/dressberry/dressberry-women-mustard-yellow-ribbed-fitted-top/11003624/buy
... A52: Textured Block Sandals with Laser Cuts | B52: ERIDANI | C52: 0 | D52: 0 | E52: 1799 | F52: 1799 | G52: EURO35,EURO36,EURO37,EURO38,EURO39,EURO40,EURO41 | H52: heels/eridani/eridani-black-textured-block-sandals-with-laser-cuts/18711914/buy
A53: Slim Fit Formal Shirt | B53: Greenfibre | C53: 0 | D53: 0 | E53: 1549 | F53: 1549 | G53: 46 | H53: shirts/greenfibre/greenfibre-men-blue-slim-fit-checked-formal-shirt/18427508/buy
A54: Coconut Conditioner 350 ml | B54: MYSTIC VALLEY | C54: 0 | D54: 0 | E54: 1425 | F54: 1425 | G54: 100-350 ML | H54: shampoo-and-conditioner/mystic-valley/mystic-valley-coconut-chimera--mineral-bays-anti-breakage-soft-hair-conditioner-350-ml/18356878/buy
A55: Solid Workout Bra | B55: Alcis | C55: 0 | D55: 0 | E55: 1899 | F55: 1899 | G55: XS,S,M,L,XL | H55: bra/alcis/alcis-lime-green--solid-workout-bra/18255544/buy
A56: Floral Maxi Dress | B56: BoStreet | C56: 0 | D56: 0 | E56: 1999 | F56: 1719 | G56: S,M,L,XL,XXL,3XL | H56: dresses/bostreet/bostreet-blue-floral-maxi-dress/18246992/buy
A57: Women Kurta Set | B57: Seerat | C57: 2.5 | D57: 4 | E57: 7900 | F57: 7110 | G57: XS,S,M,L,XL,XXL | H57: kurta-sets/seerat/seerat-women-green--yellow-ethnic-motifs-pure-silk-kurta-with-trousers--dupatta/16492866/buy
A58: Structured Handheld Bag | B58: Lavie | C58: 0 | D58: 0 | E58: 4490 | F58: 2469 | G58: M | H58: handbags/lavie/lavie-beige-textured-structured-handheld-bag/15017978/buy
A59: Dobby Weave Ruffles Detail Top | B59: Mast & Harbour | C59: 0 | D59: 0 | E59: 1499 | F59: 674 | G59: XS,S,M,L,XL | H59: tops/mast--harbour/mast--harbour-rust-red-dobby-weave-ruffles-detail-top/15287534/buy
A60: Dobby Woven Design Dupatta | B60: Juniper | C60: 4.2 | D60: 85 | E60: 1049 | F60: 314 | G60: Onesize | H60: dupatta/juniper/juniper-off-white--black-dobby-woven-design-dupatta/11478462/buy
A61: Men Slim Fit Running Sports Shorts | B61: FITINC | C61: 0 | D61: 0 | E61: 999 | F61: 499 | G61: 30,32,34,37,40 | H61: shorts/fitinc/fitinc-men-grey-slim-fit-running-sports-shorts/18355614/buy
A62: Men RCB Baseball Cap | B62: Puma | C62: 4.1 | D62: 46 | E62: 899 | F62: 494 | G62: Onesize | H62: caps/puma/puma-men-red--navy-blue-printed-royal-challengers-baseball-cap/13984064/buy
A63: Boys Floral Printed V-Neck T-shirt | B63: max | C63: 4.5 | D63: 27 | E63: 199 | F63: 199 | G63: 6-12M,12-18M,18-24M | H63: tshirts/max/max-boys-white--black-printed-v-neck-tropical-t-shirt/17425494/buy
A64: Women Analogue Watch | B64: LOIS CARON | C64: 4.2 | D64: 16 | E64: 3999 | F64: 719 | G64: Onesize | H64: watches/lois-caron/lois-caron-women-gold-toned-analogue-watch-mlc-8620/14448140/buy
A65: Women Printed Crepe Kurta | B65: KALINI | C65: 0 | D65: 0 | E65: 999 | F65: 399 | G65: S,M,L,XL,XXL,3XL,4XL | H65: kurtas/kalini/kalini-women-blue--black-printed-crepe-kurta/17075664/buy
... A260: Men Printed Cotton T-shirt | B260: Jolie robe | C260: 0 | D260: 0 | E260: 1299 | F260: 519 | G260: S,M,L,XL,XXL | H260: tshirts/jolie-robe/jolie-robe-men-charcoal-grey--green-graphic-printed-cotton-t-shirt/18103534/buy
A261: Formal Shirt | B261: JADE BLUE | C261: 0 | D261: 0 | E261: 2749 | F261: 2749 | G261: 46 | H261: shirts/jade-blue/jade-blue-men-green-formal-shirt/18428308/buy
A262: Women Analogue Watch | B262: Fossil | C262: 4.4 | D262: 81 | E262: 10995 | F262: 10995 | G262: Onesize | H262: watches/fossil/fossil-women-black-analogue-watch-es4519sor/9037953/buy
A263: Solid Shoulder Bag | B263: Lino Perros | C263: 4.4 | D263: 296 | E263: 3495 | F263: 1887 | G263: Onesize | H263: handbags/lino-perros/lino-perros-pink-solid-shoulder-bag/2155170/buy
A264: Men Polo Collar T-shirt | B264: Red Tape | C264: 0 | D264: 0 | E264: 3099 | F264: 1049 | G264: S,M,L,XL,XXL | H264: tshirts/red-tape/red-tape-men-blue-polo-collar-pure-cotton-t-shirt/17672120/buy
A265: Men Polycotton Lounge Pants | B265: max | C265: 4.8 | D265: 10 | E265: 699 | F265: 699 | G265: S,M,L,XL,XXL | H265: lounge-pants/max/max-men-navy-blue-solid-mid-rise-polycotton-lounge-pants/17593908/buy
A266: Men Typography Printed T-shirt | B266: Moda Rapido | C266: 4.2 | D266: 13 | E266: 899 | F266: 431 | G266: S,M,L,XL | H266: tshirts/moda-rapido/moda-rapido-men-pink-typography-printed-pure-cotton-t-shirt/17108186/buy
A267: Ethnic Motif A-Line Kurta | B267: mokshi | C267: 3.7 | D267: 49 | E267: 2499 | F267: 699 | G267: S,M,L,XL,XXL | H267: kurtas/mokshi/mokshi-women-navy-blue--beige-ethnic-motif-foil-print-a-line-kurta/12764720/buy
A268: Nail Lacquer - Bumble Bee | B268: Colorbar | C268: 4.5 | D268: 170 | E268: 199 | F268: 199 | G268: Onesize | H268: nail-polish/colorbar/colorbar-nail-lacquer---bumble-bee-12ml/8862403/buy
A269: Men Skinny Fit Jeans | B269: Flying Machine | C269: 0 | D269: 0 | E269: 2299 | F269: 1609 | G269: 30,32,34,36,38 | H269: jeans/flying-machine/flying-machine-men-blue-jackson-skinny-fit-mid-rise-light-fade-stretchable-jeans/17097906/buy
A270: Boys Printed Cotton Kurta | B270: House of Pataudi | C270: 0 | D270: 0 | E270: 899 | F270: 899 | G270: 8-9Y,10-11Y,11-12Y,13-14Y | H270: kurtas/house-of-pataudi/house-of-pataudi-boys-navy-blue-printed-pure-cotton-kurta/16279730/buy
A271: Leather Structured Shoulder Bag with Quilted | B271: Da Milano | C271: 0 | D271: 0 | E271: 12999 | F271: 12999 | G271: Onesize | H271: handbags/da-milano/da-milano-black-textured-leather-structured-shoulder-bag-with-quilted/18003228/buy
A272: Men Kurta | B272: CAVALLO by Linen Club | C272: 0 | D272: 0 | E272: 1899 | F272: 1329 | G272: S,M,L,XL | H272: kurtas/cavallo-by-linen-club/cavallo-by-linen-club-men-blue-thread-work-kurta/18306840/buy
A273: Pure Cotton Crop Top | B273: People | C273: 0 | D273: 0 | E273: 599 | F273: 599 | G273: XS,S,M,L,XL,XXL | H273: tops/people/people-white-printed-pure-cotton-crop-top/18129988/buy
A274: Women Trousers | B274: GOLDSTROMS | C274: 0 | D274: 0 | E274: 549 | F274: 543 | G274: 36 | H274: trousers/goldstroms/goldstroms-women-peach-coloured-trousers/18627104/buy
A275: Ethnic Motifs Saree | B275: BEATITUDE | C275: 0 | D275: 0 | E275: 20041 | F275: 14028 | G275: Onesize | H275: sarees/beatitude/beatitude-green--pink-ethnic-motif-gajji-satin-silk-saree/17712406/buy
A276: Women Silver Necklace | B276: SHAYA | C276: 0 | D276: 0 | E276: 14500 | F276: 11600 | G276: Onesize | H276: necklace-and-chains/shaya/shaya-women-silver-toned--blue-silver-necklace/15113030/buy
A277: TINT Smartwatch DSM.90002-1 | B277: Daniel Klein | C277: 3.2 | D277: 9 | E277: 6950 | F277: 2085 | G277: Onesize | H277: smart-watches/daniel-klein/daniel-klein-unisex-pink-tint-smartwatch-dsm90002-1/16871710/buy
A278: Women Cotton Night suit | B278: beebelle | C278: 0 | D278: 0 | E278: 2497 | F278: 948 | G278: S,M,L,XL,XXL | H278: night-suits/beebelle/beebelle-women-maroon--white-conversational-printed-pure-cotton-night-suit/16615886/buy
A279: Girls Embroidered Skinny Fit Jeggings | B279: Naughty Ninos | C279: 0 | D279: 0 | E279: 1699 | F279: 900 | G279: 9-10Y,11-12Y,13-14Y,14-15Y | H279: jeggings/naughty-ninos/-naughty-ninos-girls-blue-embroidered-skinny-fit-jeggings/18003070/buy
A280: Belted Peplum Layered Kurta | B280: INDYA | C280: 4.2 | D280: 14 | E280: 3200 | F280: 1600 | G280: XS,S,M,L,XL,XXL | H280: kurtas/indya/indya-women-wine-coloured-embroidered-belted-peplum-layered-kurta/13810922/buy
A281: Pure Cotton Casual Shirt | B281: Arrow | C281: 0 | D281: 0 | E281: 2399 | F281: 2399 | G281: 39,40,42,44 | H281: shirts/arrow/arrow-men-beige-tartan-checks-checked-pure-cotton-casual-shirt/16455962/buy
A282: Men Slim Fit Casual Shirt | B282: SINGLE | C282: 0 | D282: 0 | E282: 2099 | F282: 1196 | G282: 38,40,42,44,46 | H282: shirts/single/single-men-pink-placement-print-slim-fit-casual-shirt/17974320/buy
A283: Slim Fit Casual Shirt | B283: Voi Jeans | C283: 0 | D283: 0 | E283: 2499 | F283: 1024 | G283: 38,40,42,44,46 | H283: shirts/voi-jeans/voi-jeans-men-navy-blue-slim-fit-solid-casual-cotton-shirt/14287410/buy
A284: Women Embroidered Kurta with Sharara | B284: Indo Era | C284: 4.1 | D284: 14 | E284: 3999 | F284: 1679 | G284: XS,S,M,L,XL,XXL | H284: kurta-sets/indo-era/indo-era-women-burgundy-embroidered-kurta-with-sharara/15050670/buy
A285: Girls Cotton Sweatshorts | B285: H&M | C285: 0 | D285: 0 | E285: 699 | F285: 699 | G285: 2-3Y,3-4Y,4-5Y,5-6Y,6-7Y,7-8Y,8-9Y,9-10Y | H285: shorts/hm/hm-beige-girls-cotton-sweatshorts/17810200/buy
A286: Women Ethnic Motifs Printed Handloom Anarkali Kurta | B286: KALINI | C286: 0 | D286: 0 | E286: 2599 | F286: 779 | G286: S,M,L,XL,XXL | H286: kurtas/kalini/kalini-women-sea-green-ethnic-motifs-printed-gotta-patti-handloom-anarkali-kurta/18477228/buy
... A311: Lightly Padded Balconette Bra | B311: mod & shy | C311: 0 | D311: 0 | E311: 2199 | F311: 1715 | G311: 30C,32B,32C,32D,34B,34C,34D | H311: bra/mod--shy/mod--shy-beige-underwired-half-coverage-balconette-bra-/18278124/buy
A312: Slim Fit Formal Shirt | B312: METAL | C312: 0 | D312: 0 | E312: 2449 | F312: 2449 | G312: 46 | H312: shirts/metal/metal-men-peach-coloured-slim-fit-pure-cotton-formal-shirt/18407470/buy
A313: Men Self Design Kurta with Churidar | B313: DEYANN | C313: 0 | D313: 0 | E313: 5990 | F313: 2396 | G313: S,M,L,XL,XXL,3XL | H313: kurta-sets/deyann/deyann-men-blue--cream-coloured-self-design-kurta-with-churidar/10276225/buy
A314: Women Solid Top | B314: United Colors of Benetton | C314: 0 | D314: 0 | E314: 2299 | F314: 1724 | G314: XS,S,M,L,XL | H314: tops/united-colors-of-benetton/united-colors-of-benetton-women-blue-solid-top/17639894/buy
A315: Ceramic Flower Vase | B315: TAYHAA | C315: 4.1 | D315: 38 | E315: 2300 | F315: 805 | G315: Onesize | H315: vases/tayhaa/tayhaa-white-ceramic-flower-vase/9996453/buy
A316: Boxy Casual Shirt | B316: ONLY | C316: 0 | D316: 0 | E316: 2499 | F316: 1374 | G316: XS,S,M,L,XL | H316: shirts/only/only-women-yellow-boxy-gingham-checks-checked-casual-shirt/16839566/buy
A317: Embellished Top | B317: Latin Quarters | C317: 0 | D317: 0 | E317: 1699 | F317: 1189 | G317: S,M,L,XL,XXL | H317: tops/latin-quarters/latin-quarters-black-embellished-top/16975698/buy
A318: Women Printed Kurti with Palazzos | B318: saubhagya | C318: 0 | D318: 0 | E318: 4999 | F318: 1599 | G318: S,M,L,XL,XXL | H318: kurta-sets/saubhagya/saubhagya-women-green-ethnic-motifs-printed-pure-cotton-kurti-with-palazzos/17776326/buy
A319: Kids Cotton Round Neck T-shirt | B319: GOJI | C319: 3.8 | D319: 5 | E319: 1599 | F319: 239 | G319: 2-3Y,3-4Y,4-5Y,5-6Y,6-7Y,7-8Y | H319: tshirts/goji/goji-kids-navy-blue-solid-cotton-round-neck-t-shirt/15179074/buy
A320: Printed Gathered A-Line Dress | B320: URBANIC | C320: 4.7 | D320: 13 | E320: 1790 | F320: 895 | G320: M,L,XL,XXL | H320: dresses/urbanic/urbanic-black--golden-polka-dots-print-gathered-a-line-dress/15628396/buy
A321: Women Solid Top | B321: AKKRITI BY PANTALOONS | C321: 3 | D321: 5 | E321: 799 | F321: 799 | G321: XS,S,M,L,XL | H321: tops/akkriti-by-pantaloons/akkriti-by-pantaloons-women-off-white-solid-top/17302234/buy
A322: Women Set Of 2 Analogue Watch | B322: CARLINGTON | C322: 0 | D322: 0 | E322: 7999 | F322: 1599 | G322: Onesize | H322: watches/carlington/carlington-women-set-of-2-black--silver-toned-analogue-watch-ct2003-ct2010/16325498/buy
A323: Mini Straightener & Curler | B323: WAHL | C323: 2.8 | D323: 6 | E323: 2000 | F323: 1000 | G323: Onesize | H323: hair-appliance/wahl/wahl-pink-wchs6-1824-lollipop-mini-straightener--curler/13279902/buy
A324: Sheath Mini Dress | B324: Emmyrobe | C324: 3.6 | D324: 8 | E324: 3799 | F324: 999 | G324: XS,S,M,L,XL,XXL,3XL | H324: dresses/emmyrobe/emmyrobe-black-sheath-mini-dress/16022792/buy
... A535: Women Open Toe Flats | B535: FABBMATE | C535: 0 | D535: 0 | E535: 1499 | F535: 749 | G535: EURO37,EURO38,EURO39,EURO40,EURO41 | H535: flats/fabbmate/fabbmate-women-black-open-toe-flats-with-buckles/18622202/buy
A536: Men Slim Fit Casual Shirt | B536: METAL | C536: 0 | D536: 0 | E536: 1949 | F536: 1949 | G536: 46 | H536: shirts/metal/metal-men-maroon-slim-fit-printed-cotton-casual-shirt/18407494/buy
A537: Women Solid A-Line Skirt | B537: I Saw It First | C537: 0 | D537: 0 | E537: 1699 | F537: 1444 | G537: 26,28,30,32,34 | H537: skirts/i-saw-it-first/i-saw-it-first-women-beige-solid-a-line-skirt/17365718/buy
A538: Men Slim Fit Trousers | B538: V-Mart | C538: 0 | D538: 0 | E538: 1100 | F538: 880 | G538: 28,30,32,34,36,38 | H538: trousers/v-mart/v-mart-men-navy-blue-slim-fit-cotton-trousers/18129318/buy
A539: Men Shorts | B539: Trendyol | C539: 0 | D539: 0 | E539: 1899 | F539: 1424 | G539: 28,30,32,34 | H539: shorts/trendyol/trendyol-men-navy-blue-shorts/17814634/buy
A540: Sequinned Half and Half Saree | B540: Sangria | C540: 4.2 | D540: 6 | E540: 3999 | F540: 1759 | G540: Onesize | H540: sarees/sangria/sangria-mauve-embellished-sequinned-half-and-half-saree/17833182/buy
A541: Women Exotic EDT 100 ml | B541: Police | C541: 4.3 | D541: 16 | E541: 2095 | F541: 1361 | G541: 100-120 ML | H541: perfume-and-body-mist/police/police-women-exotic-eau-de-toilette-100-ml/10001665/buy
A542: Structured Shoulder Bag | B542: Metro | C542: 4.8 | D542: 11 | E542: 1690 | F542: 1098 | G542: Onesize | H542: handbags/metro/metro-grey-textured-structured-shoulder-bag/16965624/buy
A543: Slim Fit Casual Shirt | B543: Allen Solly Junior | C543: 0 | D543: 0 | E543: 1499 | F543: 974 | G543: 9-10Y,11-12Y,13-14Y,15-16Y | H543: shirts/allen-solly-junior/allen-solly-junior-boys-teal-blue-slim-fit-printed-casual-shirt/17474272/buy
A544: Men Ethnic Motifs Printed Kurta | B544: DEYANN | C544: 3.7 | D544: 36 | E544: 2990 | F544: 1046 | G544: S,M,L,XL,XXL,3XL | H544: kurtas/deyann/deyann-men-navy-blue-ethnic-motifs-printed-kurta/14201428/buy
A545: Ikat Woven Design Kurta Set | B545: Taavi | C545: 0 | D545: 0 | E545: 4099 | F545: 1844 | G545: XS,S,M,L,XL | H545: kurta-sets/taavi/taavi-women-grey-ikat-woven-design-kurta-with-trousers/15020726/buy
A546: Set of 5 Square Cushion Covers | B546: AEROHAVEN | C546: 4.3 | D546: 7 | E546: 999 | F546: 399 | G546: 16"X16" | H546: cushion-covers/aerohaven/aerohaven-multicoloured-set-of-5-digital-printed-abstract-velvet-square-cushion-covers/16914068/buy
A547: Corduroy Mini Skirt | B547: SASSAFRAS | C547: 4.4 | D547: 28 | E547: 1599 | F547: 639 | G547: 26,28,30,32,34 | H547: skirts/sassafras/sassafras-pink-corduroy-front-tie-up-mini-skirt/15940186/buy
A548: Women Floral Printed Kurta | B548: Divena | C548: 4.8 | D548: 8 | E548: 2099 | F548: 1049 | G548: 3XL,4XL,5XL,6XL | H548: kurtas/divena/divena-women-navy-blue--sea-green-printed-kurta/14687522/buy
... A853: Classic Sphere Hanging Light | B853: Homesake | C853: 0 | D853: 0 | E853: 2500 | F853: 1299 | G853: Onesize | H853: ceiling-lamps/homesake/homesake-gold-toned-solid-filament-classic-sphere-hanging-light/9019063/buy
A854: Unisex Original EDC 400 ml | B854: 4711 | C854: 0 | D854: 0 | E854: 3900 | F854: 2925 | G854: 400 ML & Above | H854: perfume-and-body-mist/4711/4711-unisex-original-edc-400-ml/1694445/buy
A855: 2 Pcs Warli Milk Mugs Set | B855: VarEesha | C855: 4.7 | D855: 9 | E855: 1099 | F855: 780 | G855: Onesize | H855: cups-and-mugs/vareesha/vareesha-brown-2-pieces-warli-stoneware-milk-shake-beer-mugs-set/6709379/buy
A856: Floral Maxi Dress | B856: The Vanca | C856: 4.1 | D856: 7 | E856: 2799 | F856: 1259 | G856: S,M,L,XL,XXL | H856: dresses/the-vanca/the-vanca-blue--red-floral-maxi-dress/15972434/buy
A857: Women Maxi Dress | B857: Zink London | C857: 4 | D857: 6 | E857: 2899 | F857: 1159 | G857: S,M,L,XL,XXL | H857: dresses/zink-london/zink-london-women-red-ditsy-floral-printed-maxi-dress/14598770/buy
A858: Solid Velvet Top | B858: SASSAFRAS | C858: 4 | D858: 33 | E858: 1399 | F858: 629 | G858: XS,S,M,L,XL | H858: tops/sassafras/sassafras-women-pretty-pink-solid-velvet-top/15940146/buy
A859: Opaque Casual Shirt | B859: Arrow Sport | C859: 0 | D859: 0 | E859: 2299 | F859: 1149 | G859: 38,39,40,42,46 | H859: shirts/arrow-sport/arrow-sport-men-green-opaque-checked-cotton-casual-shirt/15954780/buy
A860: Pack of 3 Pure Cotton Briefs | B860: DressBerry | C860: 4.2 | D860: 496 | E860: 999 | F860: 349 | G860: S,M,L,XL | H860: briefs/dressberry/dressberry-women-pack-of-3-pure-cotton-solid-briefs-db-solid-bik-new-001/14917720/buy
A861: Girls Crepe Sheath Dress | B861: Peppermint | C861: 0 | D861: 0 | E861: 1045 | F861: 731 | G861: 8-9Y,10-11Y | H861: dresses/peppermint/peppermint-girls-red-crepe-sheath-dress/16281626/buy
A862: Regular Fit Formal Shirt | B862: JADE BLUE | C862: 0 | D862: 0 | E862: 1899 | F862: 1519 | G862: 38,39,40,42,44 | H862: shirts/jade-blue/jade-blue-men-grey-pinstriped-pure-cotton-regular-fit-formal-shirt/17573308/buy
A863: Opaque Casual Shirt | B863: People | C863: 0 | D863: 0 | E863: 1399 | F863: 1399 | G863: 38,39,40,42,44,46 | H863: shirts/people/people-men-mustard-yellow--navy-blue-opaque-checked-casual-shirt/15788052/buy
A864: Women Regular Fit Denim Shorts | B864: Roadster | C864: 4.5 | D864: 137 | E864: 1499 | F864: 524 | G864: 26,28,30,32,34,36 | H864: shorts/roadster/roadster-women-blue-washed-regular-fit-denim-shorts/11688412/buy
A865: Set of 2 Perfumes | B865: Fogg | C865: 4.3 | D865: 1300 | E865: 925 | F865: 508 | G865: Pack | H865: perfume-and-body-mist/fogg/fogg-set-of-2-perfumes/9691061/buy
A866: Race Back Bodycon Mini Dress | B866: FOREVER 21 | C866: 0 | D866: 0 | E866: 999 | F866: 749 | G866: XS,S,M,L,XL | H866: dresses/forever-21/forever-21-beige-race-back-bodycon-mini-dress/17013340/buy
... A895: Printed Opaque Casual Shirt | B895: ColorPlus | C895: 0 | D895: 0 | E895: 3099 | F895: 1704 | G895: 39,40,42,44 | H895: shirts/colorplus/colorplus-men-yellow-floral-opaque-printed-casual-shirt/16275412/buy
A896: Men Leather Formal Belt | B896: United Colors of Benetton | C896: 3.4 | D896: 7 | E896: 2999 | F896: 899 | G896: 34 | H896: belts/united-colors-of-benetton/united-colors-of-benetton-men-navy-blue--tan-brown-leather-reversible-formal-belt/8488829/buy
A897: Cone Shade Armed Sconces | B897: Homesake | C897: 4.3 | D897: 21 | E897: 3300 | F897: 1199 | G897: Onesize | H897: wall-lamps/homesake/homesake-black-solid-edison-cone-shade-armed-sconces/9246303/buy
A898: Women Slim Fit Regular Trousers | B898: FORCLAZ By Decathlon | C898: 5 | D898: 6 | E898: 2999 | F898: 2579 | G898: 26,28,30,32,34,36 | H898: trousers/forclaz-by-decathlon/forclaz-by-decathlon-women-charcoal-black-slim-fit-solid-regular-trousers/13168086/buy
...

Sheet clean data 
A1: product_name | B1: brand_name | C1: rating | D1: rating_count | E1: marked_price | F1: discounted_price | G1: sizes | H1: product_category | I1: brand_symbol | J1: product_id | K1: revenue | L1: discount
A2: Pure Georgette Bandhani Saree | B2: Mitera | C2: 3.6 | D2: 5 | E2: 6727 | F2: 1681 | G2: Onesize | H2: sarees | I2: mitera | J2: 17141476 | K2: =D2*F2 -> 8405 | L2: =((E2-F2)/E2)*100 -> 75.011149
A3: Men Accessory Gift Set | B3: WildHorn | C3: 4.5 | D3: 80 | E3: 2999 | F3: 1049 | G3: Onesize | H3: accessory-gift-set | I3: wildhorn | J3: 1410357 | K3: =D3*F3 -> 83920 | L3: =((E3-F3)/E3)*100 -> 65.021674
A4: Self-Design Thermal Set | B4: Kanvin | C4: 4.6 | D4: 42 | E4: 1598 | F4: 1278 | G4: S,M,L,XL,XXL | H4: thermal-set | I4: kanvin | J4: 2223155 | K4: =D4*F4 -> 53676 | L4: =((E4-F4)/E4)*100 -> 20.025031 | O4: THIS CLEAN DATA CONTAINS ALL ROWS EXCEPT THOSE WHO HAVE 0 RATING.
A5: Men Slim Fit T-shirt | B5: Jack & Jones | C5: 3.7 | D5: 7 | E5: 1299 | F5: 649 | G5: S,M,L,XL,XXL | H5: tshirts | I5: jack--jones | J5: 15430520 | K5: =D5*F5 -> 4543 | L5: =((E5-F5)/E5)*100 -> 50.038491
A6: Outdoor Rapid-Dry Jacket | B6: HRX by Hrithik Roshan | C6: 4.4 | D6: 186 | E6: 2799 | F6: 1679 | G6: XS,S,M,L,XL | H6: jackets | I6: hrx-by-hrithik-roshan | J6: 11953112 | K6: =D6*F6 -> 312294 | L6: =((E6-F6)/E6)*100 -> 40.014291
A7: Floral Maxi Dress | B7: Nayo | C7: 4 | D7: 7 | E7: 1999 | F7: 799 | G7: S,M,L,XL,XXL | H7: dresses | I7: nayo | J7: 17634118 | K7: =D7*F7 -> 5593 | L7: =((E7-F7)/E7)*100 -> 60.030015
A8: Women Ribbed Fitted Top | B8: DressBerry | C8: 4.2 | D8: 252 | E8: 999 | F8: 399 | G8: XS,S,M,L,XL | H8: tops | I8: dressberry | J8: 11003624 | K8: =D8*F8 -> 100548 | L8: =((E8-F8)/E8)*100 -> 60.06006
A9: Men Gold-Toned Brooch | B9: Alvaro Castagnino | C9: 4.9 | D9: 10 | E9: 999 | F9: 399 | G9: Onesize | H9: brooch | I9: alvaro-castagnino | J9: 17426638 | K9: =D9*F9 -> 3990 | L9: =((E9-F9)/E9)*100 -> 60.06006
A10: Printed Lounge T-shirt | B10: ETC | C10: 4.3 | D10: 52 | E10: 499 | F10: 324 | G10: S,M,L,XL | H10: lounge-tshirts | I10: etc | J10: 12442110 | K10: =D10*F10 -> 16848 | L10: =((E10-F10)/E10)*100 -> 35.07014
A11: Men Solid Sliders | B11: Power | C11: 3.9 | D11: 34 | E11: 746 | F11: 671 | G11: UK6,UK7,UK8,UK9,UK10,UK11 | H11: flip-flops | I11: power | J11: 12453854 | K11: =D11*F11 -> 22814 | L11: =((E11-F11)/E11)*100 -> 10.053619
A12: Women Skinny Fit Jeans | B12: Mast & Harbour | C12: 4 | D12: 105 | E12: 1799 | F12: 809 | G12: 26,28,30,32,34,36 | H12: jeans | I12: mast--harbour | J12: 12310178 | K12: =D12*F12 -> 84945 | L12: =((E12-F12)/E12)*100 -> 55.030573
A13: Unisex Round Sunglasses | B13: WROGN | C13: 4.1 | D13: 338 | E13: 2899 | F13: 1884 | G13: M | H13: sunglasses | I13: wrogn | J13: 2385219 | K13: =D13*F13 -> 636792 | L13: =((E13-F13)/E13)*100 -> 35.012073
A14: Women Tummy & Thigh Shapewear | B14: Dermawear | C14: 2 | D14: 5 | E14: 1349 | F14: 1349 | G14: S,M,L,XL,XXL,3XL | H14: shapewear | I14: dermawear | J14: 17667772 | K14: =D14*F14 -> 6745 | L14: =((E14-F14)/E14)*100 -> 0
A15: Women Cotton Printed Tracksuit | B15: Duke | C15: 4.4 | D15: 14 | E15: 2995 | F15: 1797 | G15: S,M,L,XL,XXL | H15: tracksuits | I15: duke | J15: 15152634 | K15: =D15*F15 -> 25158 | L15: =((E15-F15)/E15)*100 -> 40
A16: Pack of 2 Minimizer Bras | B16: Floret | C16: 4.3 | D16: 239 | E16: 898 | F16: 853 | G16: 30C,32C,34C,36C,38C,40C | H16: bra | I16: floret | J16: 11169978 | K16: =D16*F16 -> 203867 | L16: =((E16-F16)/E16)*100 -> 5.0111359
... A369: Men Analogue Watch | B369: TIMESMITH | C369: 3.9 | D369: 7 | E369: 2499 | F369: 399 | G369: Onesize | H369: watches | I369: timesmith | J369: 11135920 | K369: =D369*F369 -> 2793 | L369: =((E369-F369)/E369)*100 -> 84.033613
A370: Men Leather Formal Belt | B370: United Colors of Benetton | C370: 3.4 | D370: 7 | E370: 2999 | F370: 899 | G370: 34 | H370: belts | I370: united-colors-of-benetton | J370: 8488829 | K370: =D370*F370 -> 6293 | L370: =((E370-F370)/E370)*100 -> 70.023341
A371: Cone Shade Armed Sconces | B371: Homesake | C371: 4.3 | D371: 21 | E371: 3300 | F371: 1199 | G371: Onesize | H371: wall-lamps | I371: homesake | J371: 9246303 | K371: =D371*F371 -> 25179 | L371: =((E371-F371)/E371)*100 -> 63.666667
A372: Women Slim Fit Regular Trousers | B372: FORCLAZ By Decathlon | C372: 5 | D372: 6 | E372: 2999 | F372: 2579 | G372: 26,28,30,32,34,36 | H372: trousers | I372: forclaz-by-decathlon | J372: 13168086 | K372: =D372*F372 -> 15474 | L372: =((E372-F372)/E372)*100 -> 14.004668
A373: Embroidered High-Low Top | B373: Mayra | C373: 3.1 | D373: 36 | E373: 1095 | F373: 459 | G373: S,M,L,XL | H373: tops | I373: mayra | J373: 11091590 | K373: =D373*F373 -> 16524 | L373: =((E373-F373)/E373)*100 -> 58.082192
A374: Printed Kurta with Palazzos | B374: FABRIC FITOOR | C374: 4.5 | D374: 15 | E374: 4599 | F374: 1057 | G374: S,M,L,XL,XXL,3XL | H374: kurta-sets | I374: fabric-fitoor | J374: 12103850 | K374: =D374*F374 -> 15855 | L374: =((E374-F374)/E374)*100 -> 77.016743
A375: Women Yoke Design Kurta with Trousers With Dupatta | B375: Varanga | C375: 1 | D375: 2 | E375: 4999 | F375: 1699 | G375: S,M,L,XL,XXL | H375: kurta-sets | I375: varanga | J375: 13983922 | K375: =D375*F375 -> 3398 | L375: =((E375-F375)/E375)*100 -> 66.013203
A376: Men Typography Printed T-shirt | B376: HERE&NOW | C376: 3.8 | D376: 5 | E376: 949 | F376: 284 | G376: S,M,L,XL | H376: tshirts | I376: herenow | J376: 16260732 | K376: =D376*F376 -> 1420 | L376: =((E376-F376)/E376)*100 -> 70.073762
A377: Unisex Anti Theft Backpack | B377: F Gear | C377: 4.5 | D377: 191 | E377: 4995 | F377: 1898 | G377: Onesize | H377: backpacks | I377: f-gear | J377: 4385679 | K377: =D377*F377 -> 362518 | L377: =((E377-F377)/E377)*100 -> 62.002002
A378: Men Solid Kurta with Pyjamas | B378: VASTRAMAY | C378: 4.4 | D378: 43 | E378: 4499 | F378: 2249 | G378: S,M,L,XL,XXL,3XL | H378: kurta-sets | I378: vastramay | J378: 4369942 | K378: =D378*F378 -> 96707 | L378: =((E378-F378)/E378)*100 -> 50.011114
A379: Girls Embroidered Kurta with Palazzos With Dupatta | B379: Biba | C379: 4.1 | D379: 7 | E379: 3299 | F379: 1649 | G379: 9Y,11Y,13Y,15Y | H379: kurta-sets | I379: biba | J379: 14847260 | K379: =D379*F379 -> 11543 | L379: =((E379-F379)/E379)*100 -> 50.015156
A380: PU Structured Sling Bag | B380: Exotic | C380: 4.7 | D380: 9 | E380: 2599 | F380: 1074 | G380: S | H380: handbags | I380: exotic | J380: 17394202 | K380: =D380*F380 -> 9666 | L380: =((E380-F380)/E380)*100 -> 58.676414
A381: AD-Studded Mangalsutra Set | B381: Brandsoon | C381: 5 | D381: 2 | E381: 2528 | F381: 353 | G381: Onesize | H381: mangalsutra | I381: brandsoon | J381: 17403044 | K381: =D381*F381 -> 706 | L381: =((E381-F381)/E381)*100 -> 86.036392
A382: Women Embroidered Rozana Kurta | B382: House of Pataudi | C382: 4.2 | D382: 5 | E382: 3199 | F382: 1919 | G382: XS,S,M,L,XL,XXL | H382: kurtas | I382: house-of-pataudi | J382: 13721048 | K382: =D382*F382 -> 9595 | L382: =((E382-F382)/E382)*100 -> 40.012504
... A717: Scoop Neck Fitted Top | B717: Miaz Lifestyle | C717: 3.5 | D717: 88 | E717: 999 | F717: 589 | G717: XS,S,M,L,XL,XXL | H717: tops | I717: miaz-lifestyle | J717: 15112544 | K717: =D717*F717 -> 51832 | L717: =((E717-F717)/E717)*100 -> 41.041041
A718: Slim Fit Casual Shirt | B718: Louis Philippe Jeans | C718: 3.3 | D718: 3 | E718: 2049 | F718: 1229 | G718: 44 | H718: shirts | I718: louis-philippe-jeans | J718: 14225978 | K718: =D718*F718 -> 3687 | L718: =((E718-F718)/E718)*100 -> 40.019522
A719: Girls Layered A-Line Dress | B719: pspeaches | C719: 4.4 | D719: 54 | E719: 1499 | F719: 524 | G719: 2-3Y,3-4Y,4-5Y,5-6Y,6-7Y,7-8Y,8-9Y,9-10Y,10-11Y,11-12Y | H719: dresses | I719: pspeaches | J719: 13882872 | K719: =D719*F719 -> 28296 | L719: =((E719-F719)/E719)*100 -> 65.043362
A720: Women Printed Kurta with Palazzos | B720: Moda Rapido | C720: 3.9 | D720: 8 | E720: 4399 | F720: 1099 | G720: XS,S,M,L,XL,XXL | H720: kurta-sets | I720: moda-rapido | J720: 14430866 | K720: =D720*F720 -> 8792 | L720: =((E720-F720)/E720)*100 -> 75.017049
A721: Suede Block Mules with Buckles | B721: VALIOSAA | C721: 3.5 | D721: 6 | E721: 2499 | F721: 1474 | G721: EURO35,EURO36,EURO37,EURO38,EURO39,EURO40 | H721: heels | I721: valiosaa | J721: 15777288 | K721: =D721*F721 -> 8844 | L721: =((E721-F721)/E721)*100 -> 41.016407
A722: Women Floral Embroidered Kurta | B722: KALINI | C722: 2.8 | D722: 5 | E722: 1249 | F722: 399 | G722: M,L,XL,XXL,3XL | H722: kurtas | I722: kalini | J722: 17227692 | K722: =D722*F722 -> 1995 | L722: =((E722-F722)/E722)*100 -> 68.054444
A723: Women Solid Block Heels | B723: Padvesh | C723: 3.4 | D723: 5 | E723: 1299 | F723: 649 | G723: EURO38,EURO39,EURO40,EURO41,EURO42 | H723: heels | I723: padvesh | J723: 12826644 | K723: =D723*F723 -> 3245 | L723: =((E723-F723)/E723)*100 -> 50.038491
A724: Women Cotton Solid Pullover | B724: MANGO | C724: 4.2 | D724: 9 | E724: 2990 | F724: 1794 | G724: XS,S,M,L | H724: sweaters | I724: mango | J724: 15721508 | K724: =D724*F724 -> 16146 | L724: =((E724-F724)/E724)*100 -> 40
A725: Women High Waist Tummy & Thigh Control Seamless Shapewear | B725: SECRETS BY ZEROKAATA | C725: 3.8 | D725: 138 | E725: 1000 | F725: 820 | G725: M,L,XL | H725: shapewear | I725: secrets-by-zerokaata | J725: 13549778 | K725: =D725*F725 -> 113160 | L725: =((E725-F725)/E725)*100 -> 18
A726: Geometric Regular Top | B726: Trend Arrest | C726: 4.2 | D726: 9 | E726: 1299 | F726: 480 | G726: XS,S,M,L,XL | H726: tops | I726: trend-arrest | J726: 16247900 | K726: =D726*F726 -> 4320 | L726: =((E726-F726)/E726)*100 -> 63.048499
A727: Satin Wrap Dress | B727: NEUDIS | C727: 3.6 | D727: 5 | E727: 2199 | F727: 791 | G727: XS,S,M,L,XL | H727: dresses | I727: neudis | J727: 16923146 | K727: =D727*F727 -> 3955 | L727: =((E727-F727)/E727)*100 -> 64.029104
A728: Men Skinny Fit Jeans | B728: Allen Solly | C728: 3.5 | D728: 2 | E728: 2799 | F728: 1931 | G728: 30,32,34,36,38 | H728: jeans | I728: allen-solly | J728: 14843430 | K728: =D728*F728 -> 3862 | L728: =((E728-F728)/E728)*100 -> 31.011075
A729: Men Solid T-shirt | B729: Moda Rapido | C729: 3.3 | D729: 6 | E729: 999 | F729: 519 | G729: S,M,L,XL | H729: tshirts | I729: moda-rapido | J729: 15822046 | K729: =D729*F729 -> 3114 | L729: =((E729-F729)/E729)*100 -> 48.048048
A730: Women Regular Top | B730: Ajile by Pantaloons | C730: 4.5 | D730: 15 | E730: 399 | F730: 399 | G730: XS,S,M,L,XL,XXL | H730: tops | I730: ajile-by-pantaloons | J730: 15375470 | K730: =D730*F730 -> 5985 | L730: =((E730-F730)/E730)*100 -> 0
... A1019: Men Sneakers | B1019: Ajile by Pantaloons | C1019: 4.4 | D1019: 9 | E1019: 1499 | F1019: 1499 | G1019: UK6,UK7,UK8,UK9,UK10 | H1019: casual-shoes | I1019: ajile-by-pantaloons | J1019: 16490752 | K1019: =D1019*F1019 -> 13491 | L1019: =((E1019-F1019)/E1019)*100 -> 0
A1020: Geometric Stone Finger Ring | B1020: Yellow Chimes | C1020: 4.4 | D1020: 40 | E1020: 1994 | F1020: 602 | G1020: 9 | H1020: ring | I1020: yellow-chimes | J1020: 15175312 | K1020: =D1020*F1020 -> 24080 | L1020: =((E1020-F1020)/E1020)*100 -> 69.809428
A1021: Striped High Neck T-shirt | B1021: Campus Sutra | C1021: 3.9 | D1021: 607 | E1021: 1199 | F1021: 719 | G1021: S,M,L,XL | H1021: tshirts | I1021: campus-sutra | J1021: 10891018 | K1021: =D1021*F1021 -> 436433 | L1021: =((E1021-F1021)/E1021)*100 -> 40.033361
A1022: Football Rapid-Dry Tshirts | B1022: HRX by Hrithik Roshan | C1022: 4 | D1022: 10 | E1022: 1199 | F1022: 779 | G1022: S,M,L,XL,XXL | H1022: tshirts | I1022: hrx-by-hrithik-roshan | J1022: 15289632 | K1022: =D1022*F1022 -> 7790 | L1022: =((E1022-F1022)/E1022)*100 -> 35.029191
A1023: Regular Checked Casual Shirt | B1023: Roadster | C1023: 4.2 | D1023: 69 | E1023: 1699 | F1023: 849 | G1023: 38,40,42,44 | H1023: shirts | I1023: roadster | J1023: 12947594 | K1023: =D1023*F1023 -> 58581 | L1023: =((E1023-F1023)/E1023)*100 -> 50.029429
A1024: Women Skinny Fit Jeans | B1024: DOLCE CRUDO | C1024: 3.9 | D1024: 152 | E1024: 2549 | F1024: 994 | G1024: 26,28,30,32,34 | H1024: jeans | I1024: dolce-crudo | J1024: 11399986 | K1024: =D1024*F1024 -> 151088 | L1024: =((E1024-F1024)/E1024)*100 -> 61.004315
A1025: Unisex Carryon Backpack | B1025: HRX by Hrithik Roshan | C1025: 4.1 | D1025: 181 | E1025: 1099 | F1025: 934 | G1025: Onesize | H1025: backpacks | I1025: hrx-by-hrithik-roshan | J1025: 11558280 | K1025: =D1025*F1025 -> 169054 | L1025: =((E1025-F1025)/E1025)*100 -> 15.013649
A1026: Women Printed T-shirt | B1026: Mast & Harbour | C1026: 4 | D1026: 14 | E1026: 999 | F1026: 299 | G1026: XS,S,M,L,XL | H1026: tshirts | I1026: mast--harbour | J1026: 13880712 | K1026: =D1026*F1026 -> 4186 | L1026: =((E1026-F1026)/E1026)*100 -> 70.07007
A1027: Print Top | B1027: Zivame | C1027: 4.3 | D1027: 8 | E1027: 645 | F1027: 290 | G1027: XXL,3XL,4XL | H1027: tops | I1027: zivame | J1027: 18056720 | K1027: =D1027*F1027 -> 2320 | L1027: =((E1027-F1027)/E1027)*100 -> 55.03876
A1028: Pack of 3 Ankle Length Socks | B1028: Artengo By Decathlon | C1028: 4.5 | D1028: 176 | E1028: 299 | F1028: 272 | G1028: UK5,UK8,UK11 | H1028: socks | I1028: artengo-by-decathlon | J1028: 14462484 | K1028: =D1028*F1028 -> 47872 | L1028: =((E1028-F1028)/E1028)*100 -> 9.0301003
A1029: Girls Printed Top With Skirt | B1029: Cutiekins | C1029: 4 | D1029: 47 | E1029: 1999 | F1029: 699 | G1029: 4-5Y,5-6Y,6-7Y,7-8Y,8-9Y,9-10Y,10-11Y | H1029: clothing-set | I1029: cutiekins | J1029: 17261676 | K1029: =D1029*F1029 -> 32853 | L1029: =((E1029-F1029)/E1029)*100 -> 65.032516
A1030: Striped Polo Collar T-shirt | B1030: WILD WEST | C1030: 4.2 | D1030: 119 | E1030: 1799 | F1030: 575 | G1030: S,M,L,XL,XXL,3XL | H1030: tshirts | I1030: wild-west | J1030: 11577432 | K1030: =D1030*F1030 -> 68425 | L1030: =((E1030-F1030)/E1030)*100 -> 68.037799
A1031: Men Textured Formal Oxfords | B1031: INVICTUS | C1031: 3.7 | D1031: 15 | E1031: 3499 | F1031: 1399 | G1031: UK6,UK7,UK8,UK9,UK10 | H1031: formal-shoes | I1031: invictus | J1031: 15747714 | K1031: =D1031*F1031 -> 20985 | L1031: =((E1031-F1031)/E1031)*100 -> 60.017148
A1032: Women Printed Sliders | B1032: Pampy Angel | C1032: 4.3 | D1032: 24 | E1032: 499 | F1032: 394 | G1032: UK4,UK5,UK6,UK7,UK8 | H1032: flip-flops | I1032: pampy-angel | J1032: 13132308 | K1032: =D1032*F1032 -> 9456 | L1032: =((E1032-F1032)/E1032)*100 -> 21.042084
... A2153: Men Clogs | B2153: WALKWAY | C2153: 3.5 | D2153: 6 | E2153: 999 | F2153: 999 | G2153: UK6,UK7,UK8,UK9,UK10,UK11 | H2153: flip-flops | I2153: walkway | J2153: 17111412 | K2153: =D2153*F2153 -> 5994 | L2153: =((E2153-F2153)/E2153)*100 -> 0
A2154: Men Reversible Belt | B2154: Tommy Hilfiger | C2154: 4.7 | D2154: 15 | E2154: 2399 | F2154: 2159 | G2154: 40 | H2154: belts | I2154: tommy-hilfiger | J2154: 2175290 | K2154: =D2154*F2154 -> 32385 | L2154: =((E2154-F2154)/E2154)*100 -> 10.004168
A2155: Men Solid Slim Fit Track Pants | B2155: Sports52 wear | C2155: 3.7 | D2155: 36 | E2155: 995 | F2155: 437 | G2155: M,L,XL,XXL,3XL | H2155: track-pants | I2155: sports52-wear | J2155: 14190682 | K2155: =D2155*F2155 -> 15732 | L2155: =((E2155-F2155)/E2155)*100 -> 56.080402
A2156: Pure Cotton Printed Night suit | B2156: Anubhutee | C2156: 4 | D2156: 358 | E2156: 2849 | F2156: 997 | G2156: S,M,L,XL,XXL | H2156: night-suits | I2156: anubhutee | J2156: 13592712 | K2156: =D2156*F2156 -> 356926 | L2156: =((E2156-F2156)/E2156)*100 -> 65.005265
A2157: Makeup Remover Cleanser 250 ml | B2157: BIODERMA | C2157: 4.6 | D2157: 48 | E2157: 990 | F2157: 990 | G2157: 100-350 ML | H2157: makeup-remover | I2157: bioderma | J2157: 2052298 | K2157: =D2157*F2157 -> 47520 | L2157: =((E2157-F2157)/E2157)*100 -> 0
A2158: Women Pack of 2 Lounge Shorts | B2158: zebu | C2158: 4.3 | D2158: 279 | E2158: 1598 | F2158: 607 | G2158: M,L,XL | H2158: lounge-shorts | I2158: zebu | J2158: 12253792 | K2158: =D2158*F2158 -> 169353 | L2158: =((E2158-F2158)/E2158)*100 -> 62.015019
A2159: Unisex Natreal Face Wash | B2159: Taavi | C2159: 4.2 | D2159: 100 | E2159: 249 | F2159: 136 | G2159: 100-350 ML | H2159: face-wash-and-cleanser | I2159: taavi | J2159: 13454612 | K2159: =D2159*F2159 -> 13600 | L2159: =((E2159-F2159)/E2159)*100 -> 45.381526
A2160: Set of 6 Abstract Printed Chair Cove | B2160: Cortina | C2160: 4 | D2160: 23 | E2160: 4498 | F2160: 1999 | G2160: Onesize | H2160: chair-cover | I2160: cortina | J2160: 13995836 | K2160: =D2160*F2160 -> 45977 | L2160: =((E2160-F2160)/E2160)*100 -> 55.558026
A2161: Women Printed Ballerinas | B2161: ZAPATOZ | C2161: 4 | D2161: 73 | E2161: 999 | F2161: 649 | G2161: EURO36,EURO37,EURO38,EURO39,EURO40,EURO41,EURO42 | H2161: flats | I2161: zapatoz | J2161: 14617398 | K2161: =D2161*F2161 -> 47377 | L2161: =((E2161-F2161)/E2161)*100 -> 35.035035
A2162: Men Sneakers | B2162: Sparx | C2162: 4.3 | D2162: 48 | E2162: 899 | F2162: 899 | G2162: UK6,UK7,UK8,UK9,UK10 | H2162: casual-shoes | I2162: sparx | J2162: 10927848 | K2162: =D2162*F2162 -> 43152 | L2162: =((E2162-F2162)/E2162)*100 -> 0
A2163: Women Solid Backpack | B2163: DressBerry | C2163: 4.6 | D2163: 61 | E2163: 2899 | F2163: 2319 | G2163: Onesize | H2163: backpacks | I2163: dressberry | J2163: 13350098 | K2163: =D2163*F2163 -> 141459 | L2163: =((E2163-F2163)/E2163)*100 -> 20.006899
A2164: Men Valentine watch | B2164: Fastrack | C2164: 4.4 | D2164: 91 | E2164: 2295 | F2164: 2295 | G2164: Onesize | H2164: watches | I2164: fastrack | J2164: 11472384 | K2164: =D2164*F2164 -> 208845 | L2164: =((E2164-F2164)/E2164)*100 -> 0
A2165: Printed Slim Fit Casual Shirt | B2165: The Indian Garage Co | C2165: 4.2 | D2165: 30 | E2165: 1749 | F2165: 699 | G2165: 38,40,42,44 | H2165: shirts | I2165: the-indian-garage-co | J2165: 15000726 | K2165: =D2165*F2165 -> 20970 | L2165: =((E2165-F2165)/E2165)*100 -> 60.034305
A2166: Mini Lipstick - All Fired Up | B2166: M.A.C | C2166: 4.6 | D2166: 414 | E2166: 1100 | F2166: 1100 | G2166: Onesize | H2166: lipstick | I2166: mac | J2166: 13216192 | K2166: =D2166*F2166 -> 455400 | L2166: =((E2166-F2166)/E2166)*100 -> 0
... A2907: Women Typography Printed T-shirt | B2907: Roadster | C2907: 2.3 | D2907: 3 | E2907: 999 | F2907: 349 | G2907: XS,S,M,L,XL | H2907: tshirts | I2907: roadster | J2907: 16962302 | K2907: =D2907*F2907 -> 1047 | L2907: =((E2907-F2907)/E2907)*100 -> 65.065065
A2908: Unisex Printed Leather Belt | B2908: Tommy Hilfiger | C2908: 4.6 | D2908: 18 | E2908: 3399 | F2908: 3399 | G2908: 44 | H2908: belts | I2908: tommy-hilfiger | J2908: 12071676 | K2908: =D2908*F2908 -> 61182 | L2908: =((E2908-F2908)/E2908)*100 -> 0
A2909: Boys Pack of 2 Solid Joggers | B2909: YK | C2909: 4 | D2909: 5 | E2909: 2099 | F2909: 2099 | G2909: 8-9Y,10-11Y,11-12Y,13-14Y | H2909: track-pants | I2909: yk | J2909: 15267456 | K2909: =D2909*F2909 -> 10495 | L2909: =((E2909-F2909)/E2909)*100 -> 0
A2910: Slim Fit Opaque Casual Shirt | B2910: HIGHLANDER | C2910: 3.8 | D2910: 213 | E2910: 1199 | F2910: 563 | G2910: 39,40,42,44 | H2910: shirts | I2910: highlander | J2910: 15896542 | K2910: =D2910*F2910 -> 119919 | L2910: =((E2910-F2910)/E2910)*100 -> 53.044204
A2911: Women Ankle Length Leggings | B2911: TAG 7 | C2911: 4.1 | D2911: 13 | E2911: 1799 | F2911: 593 | G2911: S,M,L,XL,XXL,3XL | H2911: leggings | I2911: tag-7 | J2911: 17706158 | K2911: =D2911*F2911 -> 7709 | L2911: =((E2911-F2911)/E2911)*100 -> 67.037243
A2912: Floral Jhumkas Earrings | B2912: SOHI | C2912: 4.3 | D2912: 75 | E2912: 1000 | F2912: 410 | G2912: Onesize | H2912: earrings | I2912: sohi | J2912: 16974376 | K2912: =D2912*F2912 -> 30750 | L2912: =((E2912-F2912)/E2912)*100 -> 59
A2913: Ribbed Jersey Dress | B2913: H&M | C2913: 4.1 | D2913: 8 | E2913: 1299 | F2913: 1299 | G2913: XS,S,M,L,XL | H2913: dresses | I2913: hm | J2913: 16530842 | K2913: =D2913*F2913 -> 10392 | L2913: =((E2913-F2913)/E2913)*100 -> 0
A2914: Women Solid Lounge Tshirts | B2914: Jockey | C2914: 4.4 | D2914: 87 | E2914: 499 | F2914: 499 | G2914: S,M,L | H2914: lounge-tshirts | I2914: jockey | J2914: 15039164 | K2914: =D2914*F2914 -> 43413 | L2914: =((E2914-F2914)/E2914)*100 -> 0
A2915: Women Cateye Sunglasses | B2915: DressBerry | C2915: 3.8 | D2915: 330 | E2915: 1599 | F2915: 719 | G2915: L | H2915: sunglasses | I2915: dressberry | J2915: 5595600 | K2915: =D2915*F2915 -> 237270 | L2915: =((E2915-F2915)/E2915)*100 -> 55.034396
A2916: Women Crystal Studded Brooch | B2916: Yellow Chimes | C2916: 5 | D2916: 6 | E2916: 1082 | F2916: 437 | G2916: Onesize | H2916: brooch | I2916: yellow-chimes | J2916: 17015884 | K2916: =D2916*F2916 -> 2622 | L2916: =((E2916-F2916)/E2916)*100 -> 59.61183
A2917: Regular Fit Casual Shirt | B2917: Pepe Jeans | C2917: 4.6 | D2917: 20 | E2917: 2199 | F2917: 879 | G2917: S,M,L,XL | H2917: shirts | I2917: pepe-jeans | J2917: 12513566 | K2917: =D2917*F2917 -> 17580 | L2917: =((E2917-F2917)/E2917)*100 -> 60.027285
A2918: EDGE Men Track Pants | B2918: HRX by Hrithik Roshan | C2918: 4 | D2918: 23 | E2918: 2999 | F2918: 1799 | G2918: S,M,L,XL,XXL | H2918: track-pants | I2918: hrx-by-hrithik-roshan | J2918: 14646054 | K2918: =D2918*F2918 -> 41377 | L2918: =((E2918-F2918)/E2918)*100 -> 40.013338
A2919: Women Mules Flats | B2919: DEAS | C2919: 4.3 | D2919: 133 | E2919: 999 | F2919: 599 | G2919: EURO36,EURO37,EURO38,EURO39,EURO40,EURO41,EURO42 | H2919: flats | I2919: deas | J2919: 14869308 | K2919: =D2919*F2919 -> 79667 | L2919: =((E2919-F2919)/E2919)*100 -> 40.04004
A2920: 144 TC 1 King Bedsheet with 2 Pillow Covers | B2920: Rajasthan Decor | C2920: 4.3 | D2920: 408 | E2920: 1999 | F2920: 939 | G2920: Double King | H2920: bedsheets | I2920: rajasthan-decor | J2920: 4320535 | K2920: =D2920*F2920 -> 383112 | L2920: =((E2920-F2920)/E2920)*100 -> 53.026513
... A3039: Women Embroidered Kurta with Churidar With Dupatta | B3039: Ziva Fashion | C3039: 4.2 | D3039: 16 | E3039: 2999 | F3039: 1499 | G3039: S,M,L,XL,XXL | H3039: kurta-sets | I3039: ziva-fashion | J3039: 17972212 | K3039: =D3039*F3039 -> 23984 | L3039: =((E3039-F3039)/E3039)*100 -> 50.016672
A3040: Regular Fit Casual Shirt | B3040: Louis Philippe Jeans | C3040: 4.3 | D3040: 28 | E3040: 2049 | F3040: 1229 | G3040: 44 | H3040: shirts | I3040: louis-philippe-jeans | J3040: 12848626 | K3040: =D3040*F3040 -> 34412 | L3040: =((E3040-F3040)/E3040)*100 -> 40.019522
A3041: Women Sequinned Saree Blouse | B3041: Inddus | C3041: 3.5 | D3041: 8 | E3041: 1999 | F3041: 859 | G3041: Onesize | H3041: saree-blouse | I3041: inddus | J3041: 17535092 | K3041: =D3041*F3041 -> 6872 | L3041: =((E3041-F3041)/E3041)*100 -> 57.028514
A3042: Slim Checked Shirt | B3042: The Indian Garage Co | C3042: 4.1 | D3042: 19 | E3042: 1749 | F3042: 699 | G3042: 38,40,42,44,46 | H3042: shirts | I3042: the-indian-garage-co | J3042: 12182240 | K3042: =D3042*F3042 -> 13281 | L3042: =((E3042-F3042)/E3042)*100 -> 60.034305
A3043: Colourblocked Satin Top | B3043: STREET 9 | C3043: 3.9 | D3043: 34 | E3043: 1599 | F3043: 607 | G3043: XS,S,M,L | H3043: tops | I3043: street-9 | J3043: 15884818 | K3043: =D3043*F3043 -> 20638 | L3043: =((E3043-F3043)/E3043)*100 -> 62.038774
A3044: Men Slim Fit T-shirt | B3044: Flying Machine | C3044: 4.9 | D3044: 7 | E3044: 1099 | F3044: 989 | G3044: S,M,L,XL,XXL | H3044: tshirts | I3044: flying-machine | J3044: 16746312 | K3044: =D3044*F3044 -> 6923 | L3044: =((E3044-F3044)/E3044)*100 -> 10.009099
A3045: Men Solid Biker Jacket | B3045: The Indian Garage Co | C3045: 4.2 | D3045: 50 | E3045: 6299 | F3045: 2519 | G3045: M,L,XL,XXL | H3045: jackets | I3045: the-indian-garage-co | J3045: 7272191 | K3045: =D3045*F3045 -> 125950 | L3045: =((E3045-F3045)/E3045)*100 -> 60.009525
A3046: Kids Set of Bodywash & Shampoo | B3046: Mamaearth | C3046: 4.5 | D3046: 1000 | E3046: 798 | F3046: 678 | G3046: Pack | H3046: body-wash-and-scrub | I3046: mamaearth | J3046: 13566986 | K3046: =D3046*F3046 -> 678000 | L3046: =((E3046-F3046)/E3046)*100 -> 15.037594
A3047: 144 TC 1 King Bedsheet with 2 Pillow Covers | B3047: Florida | C3047: 3.8 | D3047: 235 | E3047: 1299 | F3047: 467 | G3047: Double King | H3047: bedsheets | I3047: florida | J3047: 13782486 | K3047: =D3047*F3047 -> 109745 | L3047: =((E3047-F3047)/E3047)*100 -> 64.049269
A3048: Women Running Shoes | B3048: Campus | C3048: 2.5 | D3048: 2 | E3048: 1799 | F3048: 1574 | G3048: UK4,UK5,UK6,UK7,UK8 | H3048: sports-shoes | I3048: campus | J3048: 16807270 | K3048: =D3048*F3048 -> 3148 | L3048: =((E3048-F3048)/E3048)*100 -> 12.506948
A3049: Men Leather Textured Belt | B3049: Tommy Hilfiger | C3049: 4.1 | D3049: 24 | E3049: 2899 | F3049: 1884 | G3049: 44 | H3049: belts | I3049: tommy-hilfiger | J3049: 9146085 | K3049: =D3049*F3049 -> 45216 | L3049: =((E3049-F3049)/E3049)*100 -> 35.012073
A3050: Solid One-Shoulder Dress | B3050: Inddus | C3050: 4.2 | D3050: 16 | E3050: 5899 | F3050: 2477 | G3050: XS,S,M,L,XL,XXL | H3050: dresses | I3050: inddus | J3050: 15916416 | K3050: =D3050*F3050 -> 39632 | L3050: =((E3050-F3050)/E3050)*100 -> 58.009832
A3051: HRX-U-17 Active T-shirt | B3051: HRX by Hrithik Roshan | C3051: 4.8 | D3051: 13 | E3051: 1199 | F3051: 1199 | G3051: 8-9Y,10-11Y,12-13Y,14-15Y,16-17Y | H3051: tshirts | I3051: hrx-by-hrithik-roshan | J3051: 14701892 | K3051: =D3051*F3051 -> 15587 | L3051: =((E3051-F3051)/E3051)*100 -> 0
A3052: Women Empire Midi Dress | B3052: IMARA | C3052: 3.9 | D3052: 10 | E3052: 1999 | F3052: 999 | G3052: S,M,L,XL,XXL | H3052: dresses | I3052: imara | J3052: 15271626 | K3052: =D3052*F3052 -> 9990 | L3052: =((E3052-F3052)/E3052)*100 -> 50.025013
...

Sheet analysis
C2: UNCLEAN DATA | G2: CLEAN DATA
C3: Total Number of Products | D3: =COUNTA(#REF!) -> 1 | G3: Total Number of Products | H3: =COUNTA(#REF!) -> 1
C4: Number of Unique Brands | D4: =COUNTA(_xlfn.UNIQUE(#REF!)) -> 1 | G4: Number of Unique Brands | H4: 2139
C5: Average Rating | D5: =AVERAGE(Sheet1!C2:C24325) -> 2.1832264 | G5: Average Rating | H5: =AVERAGE('clean data '!C2:C11439) -> 4.1597744
C6: Most Expensive Product (MP) | D6: =MAX(Sheet1!E1:E24325) -> 44950 | G6: Most Expensive Product (MP) | H6: =MAX('clean data '!E2:E11439) -> 33900
C7: Least Expensive Product (MP) | D7: =MIN(Sheet1!E2:E24325) -> 55 | G7: Least Expensive Product (MP) | H7: =MIN('clean data '!E2:E11439) -> 55
C8: Most Expensive Product (DP) | D8: =MAX(Sheet1!F2:F24325) -> 40900 | G8: Most Expensive Product (DP) | H8: =MAX('clean data '!F2:F11439) -> 33900
C9: Least Expensive Product (DP) | D9: =MIN(Sheet1!F2:F24325) -> 49 | G9: Least Expensive Product (DP) | H9: =MIN('clean data '!F2:F11439) -> 49
C10: Total Traffic on Platform | D10: =SUM(Sheet1!D2:D24325) -> 1558289 | G10: Total Traffic on Platform | H10: =SUM('clean data '!D2:D11439) -> 1404665

Sheet pivot concept
A3: brand_name | B3: Average of rating | E3: brand_name | F3: Sum of rating_count
A4: Bitterlime | B4: 4.1083333 | E4: Bitterlime | F4: 1163
A5: Blush 9 Maternity | B5: 4.45 | E5: Blush 9 Maternity | F5: 204
A6: Bodycare Kids | B6: 4.5857143 | E6: Bodycare Kids | F6: 386
A7: Dollar Bigboss | B7: 4.0333333 | E7: Dollar Bigboss | F7: 306
A8: DOT & KEY | B8: 4.6 | E8: DOT & KEY | F8: 40
A9: Grand Total | B9: 4.28 | E9: Grand Total | F9: 2099

Sheet brand_pivot
E1: BRAND PIVOT
A3: brand_name | B3: Average of marked_price | C3: Average of discounted_price | E3: brand_name | F3: Average of rating | H3: brand_name | I3: Sum of rating_count | K3: brand_name | L3: Sum of revenue | N3: brand_name | O3: Count of product_category
A4: Jockey | B4: 547.23077 | C4: 547.23077 | E4: Jockey | F4: 4.4358974 | H4: Jockey | I4: 7629 | K4: Jockey | L4: 3783102 | N4: Jockey | O4: 78
A5: Louis Philippe | B5: 3531.3729 | C5: 2568.3898 | E5: Louis Philippe | F5: 4.2 | H5: Louis Philippe | I5: 3210 | K5: Louis Philippe | L5: 5693266 | N5: Louis Philippe | O5: 59
A6: Mast & Harbour | B6: 1860.5385 | C6: 826.76154 | E6: Mast & Harbour | F6: 4.0996154 | H6: Mast & Harbour | I6: 21292 | K6: Mast & Harbour | L6: 16617334 | N6: Mast & Harbour | O6: 260
A7: Nike | B7: 2895 | C7: 2796.2308 | E7: Nike | F7: 4.4307692 | H7: Nike | I7: 306 | K7: Nike | L7: 766322 | N7: Nike | O7: 13
A8: Wildcraft | B8: 3123.037 | C8: 2954 | E8: Wildcraft | F8: 4.3407407 | H8: Wildcraft | I8: 1298 | K8: Wildcraft | L8: 3237483 | N8: Wildcraft | O8: 27
A9: Grand Total | B9: 1960.4851 | C9: 1202.0275 | E9: Grand Total | F9: 4.1979405 | H9: Grand Total | I9: 33735 | K9: Grand Total | L9: 30097507 | N9: Grand Total | O9: 437

Sheet brand_dashboard
H2: BRAND DASHBOARD

Sheet product_pivot
H2: PRODUCT PIVOT
B5: product_category | C5: Average of marked_price | D5: Average of discounted_price | F5: product_category | G5: Sum of rating_count | I5: product_category | J5: Count of brand_name
B6: jeans | C6: 2328.7133 | D6: 1275.763 | F6: jeans | G6: 34767 | I6: jeans | J6: 422
B7: shirts | C7: 1947.2538 | D7: 1066.9015 | F7: shirts | G7: 48765 | I7: shirts | J7: 650
B8: shorts | C8: 1401.4837 | D8: 851.89302 | F8: shorts | G8: 11559 | I8: shorts | J8: 215
B9: speakers | C9: 3197.2 | D9: 1619 | F9: speakers | G9: 471 | I9: speakers | J9: 5
B10: tshirts | C10: 1207.0473 | D10: 677.15254 | F10: tshirts | G10: 94149 | I10: tshirts | J10: 1121
B11: Grand Total | C11: 1624.0518 | D11: 904.3506 | F11: Grand Total | G11: 189711 | I11: Grand Total | J11: 2413

Sheet product_dashboard
J1: PRODUCT DASHBOARD
